<?xml version="1.0" encoding="utf-8" ?><dwsync><file name="contents.htm" server="ftp17.gmoserver.jp/tunagu.or.jp/" local="3672957137" remote="321138389181849852" Dst="-1" /><file name="yukisangyou-shashoku.htm" server="ftp17.gmoserver.jp/tunagu.or.jp/" local="3672957938" remote="321138389181850572" Dst="-1" /><file name="yunikemi-shashoku.htm" server="ftp17.gmoserver.jp/tunagu.or.jp/" local="3672956716" remote="321138389181849852" Dst="-1" /><file name="events.htm" server="ftp17.gmoserver.jp/tunagu.or.jp/" local="3672957082" remote="321138389181849852" Dst="-1" /><file name="koeisangyou-shashoku.htm" server="ftp17.gmoserver.jp/tunagu.or.jp/" local="3672956940" remote="321138389181849852" Dst="-1" /><file name="aboutus.htm" server="ftp17.gmoserver.jp/tunagu.or.jp/" local="3672957189" remote="321138389181849852" Dst="-1" /><file name="access.htm" server="ftp17.gmoserver.jp/tunagu.or.jp/" local="3672957170" remote="321138389181849852" Dst="-1" /><file name="bbq-event.htm" server="ftp17.gmoserver.jp/tunagu.or.jp/" local="3672957152" remote="321138389181849852" Dst="-1" /><file name="daitoutsushou-shashoku.htm" server="ftp17.gmoserver.jp/tunagu.or.jp/" local="3672957120" remote="321138389181849852" Dst="-1" /><file name="event_coming_soon.htm" server="ftp17.gmoserver.jp/tunagu.or.jp/" local="3672957099" remote="321138389181849852" Dst="-1" /><file name="gakushoku5.htm" server="ftp17.gmoserver.jp/tunagu.or.jp/" local="3672957066" remote="321138389181849912" Dst="-1" /><file name="gallet-shashoku.htm" server="ftp17.gmoserver.jp/tunagu.or.jp/" local="3672957856" remote="321138389181850572" Dst="-1" /><file name="hamanishidenki-shashoku.htm" server="ftp17.gmoserver.jp/tunagu.or.jp/" local="3672957032" remote="321138389181849912" Dst="-1" /><file name="igetadou-shashoku.htm" server="ftp17.gmoserver.jp/tunagu.or.jp/" local="3672957010" remote="321138389181849852" Dst="-1" /><file name="index.htm" server="ftp17.gmoserver.jp/tunagu.or.jp/" local="3672956992" remote="321138389181849852" Dst="-1" /><file name="jsp-shashoku.htm" server="ftp17.gmoserver.jp/tunagu.or.jp/" local="3672957797" remote="321138389181850572" Dst="-1" /><file name="kawaidenki-shashoku.htm" server="ftp17.gmoserver.jp/tunagu.or.jp/" local="3672957932" remote="321138389181850572" Dst="-1" /><file name="kyouryou-shashoku.htm" server="ftp17.gmoserver.jp/tunagu.or.jp/" local="3672957941" remote="321138389181850572" Dst="-1" /><file name="togari-shashoku.htm" server="ftp17.gmoserver.jp/tunagu.or.jp/" local="3672957695" remote="321138389181850692" Dst="-1" /><file name="yahex-shashoku.htm" server="ftp17.gmoserver.jp/tunagu.or.jp/" local="3672956841" remote="321138389181849852" Dst="-1" /><file name="office-intr.htm" server="ftp17.gmoserver.jp/tunagu.or.jp/" local="3672956893" remote="321138389181849852" Dst="-1" /><file name=".gitignore" server="ftp17.gmoserver.jp/tunagu.or.jp/" local="3659923575" remote="320980059500818128" Dst="-1" /><file name="nodaki-shashoku.htm" server="ftp17.gmoserver.jp/tunagu.or.jp/" local="3672956909" remote="321138389181849852" Dst="-1" /></dwsync>